spotckup/__init__.py
spotckup/authorize.py
spotckup/cli.py
spotckup/decorators.py
spotckup/library.py
spotckup/playlists.py
spotckup/refresh.py
spotckup/restore_library.py
spotckup/restore_playlists.py
spotckup/utils.py
spotckup-0.1.2.dist-info/LICENSE
spotckup-0.1.2.dist-info/METADATA
spotckup-0.1.2.dist-info/WHEEL
spotckup-0.1.2.dist-info/entry_points.txt
spotckup-0.1.2.dist-info/top_level.txt
spotckup-0.1.2.dist-info/RECORD
