Metadata-Version: 2.1
Name: spotckup
Version: 0.1.2
Summary: A small utility for creating JSON local backups of music and playlists from spotify
Home-page: https://github.com/mattiaforc/spotckup
Author: mattiaforc
Author-email: mattiaforc@gmail.com
License: UNKNOWN
Keywords: spotify backup utility json store
Platform: UNKNOWN
Classifier: Programming Language :: Python :: 3
Classifier: License :: OSI Approved :: MIT License
Classifier: Operating System :: OS Independent
Requires-Python: >=3.6
Requires-Dist: Click
Requires-Dist: certifi
Requires-Dist: idna
Requires-Dist: requests
Requires-Dist: urllib3
